entari_plugin_arkgacha-0.3.0.dist-info/METADATA
entari_plugin_arkgacha-0.3.0.dist-info/WHEEL
entari_plugin_arkgacha-0.3.0.dist-info/entry_points.txt
entari_plugin_arkgacha-0.3.0.dist-info/licenses/LICENSE
entari_plugin_arkgacha/README.md
entari_plugin_arkgacha/__init__.py
entari_plugin_arkgacha-0.3.0.dist-info/RECORD
