Metadata-Version: 2.1
Name: entari-plugin-arkgacha
Version: 0.3.0
Summary: Entari plugin for arknights gacha
Author-Email: RF-Tar-Railt <rf_tar_railt@qq.com>
License: MIT
Requires-Python: >=3.10
Requires-Dist: arclet-entari<0.17.0,>=0.16.0
Requires-Dist: arknights-toolkit>=0.7.7
